README.md
setup.py
nfl_stat_explorer/League.py
nfl_stat_explorer/Team.py
nfl_stat_explorer/__init__.py
nfl_stat_explorer.egg-info/PKG-INFO
nfl_stat_explorer.egg-info/SOURCES.txt
nfl_stat_explorer.egg-info/dependency_links.txt
nfl_stat_explorer.egg-info/not-zip-safe
nfl_stat_explorer.egg-info/top_level.txt