Metadata-Version: 1.0
Name: nfl-stat-explorer
Version: 0.1
Summary: Explore Team and Player Statistics
Home-page: UNKNOWN
Author: UNKNOWN
Author-email: UNKNOWN
License: UNKNOWN
Platform: UNKNOWN
